{
  "activeGraphId":1,
  "currentGraphID":1,
  "debugEnabled":false,
  "description":"This example shows you how to set up the groundmarkers node to lead the player to a location.",
  "frecency":{},
  "graphs":{
    "1":{
      "children":{},
      "description":"This is the description for graph New State",
      "dirty":false,
      "links":[
        [
          2,
          "flow",
          8,
          "flow",
          false
        ],
        [
          9,
          "value",
          8,
          "levelPath",
          false
        ],
        [
          8,
          "flow",
          10,
          "flow",
          false
        ],
        [
          11,
          "model",
          10,
          "model",
          false
        ],
        [
          11,
          "config",
          10,
          "config",
          false
        ],
        [
          12,
          "pos",
          10,
          "pos",
          false
        ],
        [
          12,
          "rot",
          10,
          "rot",
          false
        ],
        [
          10,
          "flow",
          13,
          "flow",
          false
        ],
        [
          31,
          "flow",
          28,
          "flow",
          false
        ],
        [
          30,
          "enter",
          28,
          "reset",
          false
        ],
        [
          29,
          "pos",
          28,
          "pos",
          false
        ],
        [
          13,
          "flow",
          30,
          "flow",
          false
        ],
        [
          29,
          "pos",
          30,
          "position",
          false
        ],
        [
          29,
          "scl",
          30,
          "scale",
          false
        ],
        [
          10,
          "vehId",
          30,
          "vehId",
          false
        ],
        [
          30,
          "flow",
          31,
          "flow",
          false
        ],
        [
          30,
          "enter",
          31,
          "off",
          false
        ]
      ],
      "name":"New State",
      "nodes":{
        "2":{
          "type":"events/onUpdate",
          "data":{},
          "hiddenPins":{
            "p_in":{},
            "p_out":{
              "dtRaw":true,
              "dtReal":true,
              "dtSim":true,
              "enterState":false,
              "exitState":false,
              "flow":false
            }
          },
          "pos":[
            -2117,
            51
          ]
        },
        "8":{
          "type":"util/loadLevel",
          "data":{
            "customLoadingScreen":false,
            "delayBufferFrames":0,
            "forceLevelLoad":true,
            "noLoadInEdit":true,
            "preventPlayerSpawning":true,
            "stopRunningOnClientEndMission":false
          },
          "hiddenPins":{
            "p_in":{
              "flow":false,
              "levelPath":false
            },
            "p_out":{
              "flow":false
            }
          },
          "pos":[
            -1422,
            78
          ]
        },
        "9":{
          "data":{},
          "hiddenPins":{
            "p_in":{},
            "p_out":{
              "value":false
            }
          },
          "multiLine":false,
          "pos":[
            -1697,
            191
          ],
          "string":"east_coast_usa",
          "type":"types/string"
        },
        "10":{
          "type":"vehicle/spawnVehicle",
          "data":{},
          "hiddenPins":{
            "p_in":{
              "color":true,
              "config":false,
              "dontDelete":true,
              "flow":false,
              "keepCurrent":true,
              "licenseText":true,
              "model":false,
              "name":true,
              "pos":false,
              "replaceCurrent":true,
              "reset":true,
              "rot":false
            },
            "p_out":{
              "flow":false,
              "loaded":false,
              "vehId":false
            }
          },
          "pos":[
            -498,
            78
          ]
        },
        "11":{
          "config":"TT_RWD_S_M",
          "configName":"SBR4 RWD TT S (M)",
          "configPath":"vehicles/sbr/TT_RWD_S_M.pc",
          "data":{},
          "hiddenPins":{
            "p_in":{},
            "p_out":{
              "config":false,
              "model":false
            }
          },
          "model":"sbr",
          "modelName":"SBR4",
          "pos":[
            -815,
            135
          ],
          "type":"vehicle/vehicleConfigProvider",
          "vehType":"Car"
        },
        "12":{
          "data":{},
          "displayMode":"fullBox",
          "hiddenPins":{
            "p_in":{},
            "p_out":{
              "pos":false,
              "rot":false,
              "scl":false
            }
          },
          "markerClr":[
            1,
            0,
            0.5,
            0.25
          ],
          "mode":"gizmo",
          "pos":[
            -675,
            247
          ],
          "position":[
            616.41748,
            -191.793732,
            53.4543419
          ],
          "rotation":[
            0,
            0,
            0.914607171,
            0.404343571
          ],
          "scale":[
            1,
            1,
            1
          ],
          "type":"types/transform",
          "useQuatForRotation":false
        },
        "13":{
          "type":"util/hideLoadingScreen",
          "data":{},
          "hiddenPins":{
            "p_in":{
              "flow":false,
              "reset":true
            },
            "p_out":{
              "flow":false
            }
          },
          "pos":[
            104,
            78
          ]
        },
        "28":{
          "data":{
            "step":8,
            "color":[
              0.2,
              0.53,
              1,
              1
            ],
            "fadeEnd":150,
            "fadeStart":100
          },
          "hardcodedPins":{
            "color":{
              "type":"color",
              "value":[
                0.2,
                0.53,
                1,
                1
              ]
            }
          },
          "hiddenPins":{
            "p_in":{
              "color":true,
              "cutOffDrivability":true,
              "flow":false,
              "penaltyAboveCutoff":true,
              "penaltyBelowCutoff":true,
              "pos":false,
              "reset":false,
              "waypoint":true
            },
            "p_out":{}
          },
          "pos":[
            1532,
            218
          ],
          "type":"gameplay/groundmarkers"
        },
        "29":{
          "data":{},
          "displayMode":"default",
          "hiddenPins":{
            "p_in":{},
            "p_out":{
              "pos":false,
              "rot":true,
              "scl":false
            }
          },
          "markerClr":[
            1,
            0,
            0.5,
            0.25
          ],
          "mode":"gizmo",
          "pos":[
            627,
            275
          ],
          "position":[
            707.61969,
            -505.447174,
            57.229702
          ],
          "rotation":[
            0,
            0,
            0,
            1
          ],
          "scale":[
            5,
            5,
            5
          ],
          "type":"types/transform",
          "useQuatForRotation":false
        },
        "30":{
          "data":{
            "debug":false
          },
          "hiddenPins":{
            "p_in":{
              "flow":false,
              "position":false,
              "rotation":true,
              "scale":false,
              "vehId":false
            },
            "p_out":{
              "enter":false,
              "exit":true,
              "flow":false,
              "inside":true,
              "vehId":true
            }
          },
          "pos":[
            846,
            78
          ],
          "triggerType":"Sphere",
          "type":"events/customizedTriggerBox"
        },
        "31":{
          "data":{},
          "hiddenPins":{
            "p_in":{
              "flow":false,
              "off":false,
              "on":false
            },
            "p_out":{
              "flow":false
            }
          },
          "on":true,
          "pos":[
            1294,
            64
          ],
          "type":"logic/flowSwitch"
        },
        "63":{
          "alpha":0.800000012,
          "backgroundColor":[
            0.5,
            0.5,
            0.5,
            0.5
          ],
          "borderColor":[
            0.800000012,
            0.800000012,
            0.800000012,
            1
          ],
          "commentSize":[
            754,
            645
          ],
          "commentText":"This part loads the east_coast_usa level.\\nThe \"Load Level\" node has the \"customLoadingScreen\" field set to true.\\nThis means we have to hide the loading screen when we completed loading the remaining assets.\\nThe node will only let the flow through once the level is loaded.",
          "commentTitle":"Loading Level",
          "data":{},
          "moveMode":"withNodes",
          "pos":[
            -1834,
            -182
          ],
          "simple":false,
          "textColor":[
            1,
            1,
            1,
            1
          ],
          "type":"debug/comment"
        },
        "64":{
          "alpha":0.800000012,
          "backgroundColor":[
            0.5,
            0.5,
            0.5,
            0.5
          ],
          "borderColor":[
            0.800000012,
            0.800000012,
            0.800000012,
            1
          ],
          "commentSize":[
            852,
            645
          ],
          "commentText":"This spawns a vehicle for the player.\\nYou can select which vehicle through the \"Vehicle Config Provider\" node.\\nYou can also change where the vehicle spawns through the \"Transform\" node.\\nThe node only lets the flow through once the vehicle is spawned completely.\\nIt also gives you the vehicle id, which is needed to interacit with the vehicle through nodes.\\n\\nIn the \"Spawn Vehicle\" node, you can also set additional properties of the vehicle, such as colour, and licence plate text.",
          "commentTitle":"Vehicle Spawn",
          "data":{},
          "moveMode":"withNodes",
          "pos":[
            -952,
            -182
          ],
          "simple":false,
          "textColor":[
            1,
            1,
            1,
            1
          ],
          "type":"debug/comment"
        },
        "65":{
          "alpha":0.800000012,
          "backgroundColor":[
            0.5,
            0.5,
            0.5,
            0.5
          ],
          "borderColor":[
            0.800000012,
            0.800000012,
            0.800000012,
            1
          ],
          "commentSize":[
            404,
            645
          ],
          "commentText":"Now that all additional assets have been loaded, \\nwe can hide the loading screen.\\n\\nNote: If we don't use the \"customLoadingScreen\" \\nflag in the \"Load Level\" node, the loading screen will \\ngo away before we spawn the vehicle. This means the \\nplayer will briefly see the level without the vehicle and \\nnotice the small loading delay when the vehicle is spawned.",
          "commentTitle":"Loading Level Completion",
          "data":{},
          "moveMode":"withNodes",
          "pos":[
            0,
            -182
          ],
          "simple":false,
          "textColor":[
            1,
            1,
            1,
            1
          ],
          "type":"debug/comment"
        },
        "66":{
          "alpha":0.800000012,
          "backgroundColor":[
            0.5,
            0.5,
            0.5,
            0.5
          ],
          "borderColor":[
            0.800000012,
            0.800000012,
            0.800000012,
            1
          ],
          "commentSize":[
            1188,
            771
          ],
          "commentText":"With this system you will be able to show the shortest path from the vehicle to the selected destination.\\n\\nIn order to select this destination, we create a \"Transform\" node to indicate the position of it. \\n\\nFinally, we connect the flow to the \"GroundMarkers\" node and specify the position through the \"Transform\" node.\\n\\nNote: These \"Custom Trigger\" and \"Flow Switch\" nodes are not necessary for the implementation of the \"GroundMarker\" node, but this way you will be able to stop \\nthe flow of the \"Groundmarker\" once the vehicle reaches the destination.\\nTo achieve this, we can introduce the \"Flow Switch\" node that will allow you to stop the execution of the next node depending on the conditions that you introduce \\nin the connections ON and OFF.\\nIn this case, the ON connection can be empty.\\nOn the other hand, the OFF connection will be activated when the vehicle has entered the \"Custom Trigger\" boundaries. This \"Custom Trigger\" node will detect whenever \\nthe vehicle is in the boundary of the trigger. The boundary is determinated by the same \"Transform\" node you used for the \"GroundMarker\" node.\\n",
          "commentTitle":"GroundMarker",
          "data":{},
          "moveMode":"withNodes",
          "pos":[
            560,
            -294
          ],
          "simple":false,
          "textColor":[
            1,
            1,
            1,
            1
          ],
          "type":"debug/comment"
        }
      },
      "showTab":true,
      "type":"graph",
      "variables":{},
      "viewPos":[
        -428.759857,
        -208.807785
      ],
      "viewZoom":0.200000003
    },
    "3":{
      "children":{},
      "description":"This is the description for graph States",
      "dirty":false,
      "isStateGraph":true,
      "links":[
        [
          5,
          "flow",
          4,
          "flow",
          false
        ]
      ],
      "name":"States",
      "nodes":{
        "4":{
          "data":{},
          "hiddenPins":{
            "p_in":{
              "flow":false
            },
            "p_out":{
              "fail":false,
              "success":false
            }
          },
          "pins":[
            {
              "1":"out",
              "2":"state",
              "3":"success",
              "5":"This is a flow pin."
            },
            {
              "1":"out",
              "2":"state",
              "3":"fail",
              "5":"This is a flow pin."
            },
            {
              "1":"in",
              "2":"state",
              "3":"flow",
              "5":"This is a flow pin."
            }
          ],
          "pos":[
            -22,
            -6
          ],
          "targetGraphId":1,
          "type":"states/stateNode"
        },
        "5":{
          "type":"states/stateEntry",
          "data":{},
          "hiddenPins":{
            "p_in":{},
            "p_out":{
              "flow":false
            }
          },
          "pos":[
            -400,
            0
          ]
        },
        "6":{
          "data":{},
          "hiddenPins":{
            "p_in":{
              "flow":false
            },
            "p_out":{}
          },
          "pins":[
            {
              "1":"in",
              "2":"state",
              "3":"flow",
              "5":"This is a flow pin."
            }
          ],
          "pos":[
            400,
            0
          ],
          "transitionName":"success",
          "type":"states/stateExit"
        }
      },
      "showTab":true,
      "type":"graph",
      "variables":{},
      "viewPos":[
        -415.634369,
        -397.379761
      ],
      "viewZoom":0.74999994
    }
  },
  "macros":{},
  "name":"GroundMarkerExample",
  "savedDir":"/lua/ge/extensions/flowgraph/examples/nodes/groundmarkers/",
  "savedFilename":"GroundMarkerExample.flow.json",
  "stateGraphId":3,
  "variables":{},
  "version":0.1
}